README.txt
setup.py
actg/__init__.py
actg/__main__.py
actg/messages.py
actg/processes.py
actg.egg-info/PKG-INFO
actg.egg-info/SOURCES.txt
actg.egg-info/dependency_links.txt
actg.egg-info/entry_points.txt
actg.egg-info/not-zip-safe
actg.egg-info/requires.txt
actg.egg-info/top_level.txt
actg/biofiles/__init__.py
actg/biofiles/bam.py
actg/biofiles/bed.py
actg/biofiles/file_class.py
actg/biofiles/tab.py
actg/biofiles/vcf.py
actg/dbs/__init__.py
actg/dbs/ensembl_db.py
actg/dbs/ucsc_db.py
actg/dbs/tests/__init__.py
actg/dbs/tests/test_001.py
actg/pipeline/__init__.py
actg/tools/__init__.py
actg/tools/biodata.py
actg/tools/database.py
actg/tools/system_func.py
actg/tools/utils.py
actg/tools/utils/__init__.py
actg/tools/utils/configuration.py
actg/utils/__init__.py
actg/utils/utils.py